genlm/bytes/__init__.py
genlm/bytes/trie.py
genlm/bytes/util.py
genlm/bytes/byte_lm/__init__.py
genlm/bytes/byte_lm/beam.py
genlm/bytes/byte_lm/lm_state.py
genlm/bytes/byte_lm/trie_state.py
genlm_bytes-0.1.1.dist-info/licenses/LICENSE
genlm_bytes-0.1.1.dist-info/METADATA
genlm_bytes-0.1.1.dist-info/WHEEL
genlm_bytes-0.1.1.dist-info/top_level.txt
genlm_bytes-0.1.1.dist-info/RECORD
