Metadata-Version: 2.4
Name: genlm-bytes
Version: 0.1.1
Summary: Algorithms for byte-level language modeling
Author: Tim Vieira
Author-email: Ben LeBrun <benlebrun1@gmail.com>
Requires-Python: >=3.11
License-File: LICENSE
Requires-Dist: genlm-backend>=0.1.1
Requires-Dist: arsenal
Requires-Dist: IPython
Provides-Extra: test
Requires-Dist: coverage; extra == "test"
Requires-Dist: pytest; extra == "test"
Requires-Dist: pytest-benchmark; extra == "test"
Requires-Dist: pytest-asyncio; extra == "test"
Requires-Dist: pytest-cov; extra == "test"
Requires-Dist: hypothesis; extra == "test"
Provides-Extra: docs
Requires-Dist: mkdocs; extra == "docs"
Requires-Dist: mkdocstrings[python]; extra == "docs"
Requires-Dist: mkdocs-material; extra == "docs"
Requires-Dist: mkdocs-gen-files; extra == "docs"
Requires-Dist: mkdocs-literate-nav; extra == "docs"
Requires-Dist: mkdocs-section-index; extra == "docs"
Requires-Dist: mkdocs-jupyter; extra == "docs"
Provides-Extra: bench
Requires-Dist: datasets; extra == "bench"
Dynamic: license-file
